zyplib-0.8.4.dist-info/METADATA
zyplib-0.8.4.dist-info/WHEEL
zyplib-0.8.4.dist-info/entry_points.txt
zyplib/__init__.py
zyplib/_config.py
zyplib/annotation/__init__.py
zyplib/annotation/event.py
zyplib/apps/_utils.py
zyplib/apps/annotators.py
zyplib/apps/select_file.py
zyplib/cli.py
zyplib/dataset/__init__.py
zyplib/dataset/labels.py
zyplib/dataset/make_xy_pipeline.py
zyplib/dataset/split.py
zyplib/dataset/summary.py
zyplib/dataset/torch.py
zyplib/feature/__init__.py
zyplib/feature/freq.py
zyplib/feature/tabular.py
zyplib/feature/temporal.py
zyplib/functions.py
zyplib/io/__init__.py
zyplib/io/edf.py
zyplib/io/edfbrowser.py
zyplib/io/interface/__init__.py
zyplib/io/interface/_base.py
zyplib/io/interface/edf_file.py
zyplib/io/interface/mat_file.py
zyplib/io/misc.py
zyplib/io/scoreddata.py
zyplib/io/std_data.py
zyplib/metrics/__init__.py
zyplib/metrics/fid.py
zyplib/nn/__init__.py
zyplib/nn/funcs/signal.py
zyplib/nn/insight.py
zyplib/nn/models/__init__.py
zyplib/nn/models/deprecated/eegnet_aml.py
zyplib/nn/models/eegnet.py
zyplib/nn/models/lenet.py
zyplib/nn/models/resnet.py
zyplib/nn/models/simple_cnn.py
zyplib/nn/models/simple_rnn.py
zyplib/nn/models/tcn.py
zyplib/nn/modules/__init__.py
zyplib/nn/modules/attention/CBAM.py
zyplib/nn/modules/base.py
zyplib/nn/modules/conv.py
zyplib/nn/modules/norm.py
zyplib/nn/modules/senet.py
zyplib/nn/utils/__init__.py
zyplib/nn/utils/shapes.py
zyplib/preprocessing/__init__.py
zyplib/preprocessing/coding.py
zyplib/preprocessing/filter.py
zyplib/preprocessing/resample.py
zyplib/preprocessing/scale.py
zyplib/preprocessing/segment.py
zyplib/signal/__init__.py
zyplib/signal/filter.py
zyplib/signal/psd.py
zyplib/train/__init__.py
zyplib/train/fabric/__init__.py
zyplib/train/fabric/callbacks.py
zyplib/train/fabric/logger.py
zyplib/train/fabric/procedure.py
zyplib/train/fabric/trainer.py
zyplib/train/lightning_modules/__init__.py
zyplib/train/lightning_modules/basic_trainer.py
zyplib/train/metric/__init__.py
zyplib/train/metric/torch_metric.py
zyplib/train/utils.py
zyplib/train/vanilla/__init__.py
zyplib/train/vanilla/basic_trainer.py
zyplib-0.8.4.dist-info/RECORD
