Metadata-Version: 2.1
Name: zyplib
Version: 0.8.4
Summary: Common utilites code of myself
Author: yp.z
License: AGPL
Classifier: Development Status :: 4 - Beta
Classifier: Intended Audience :: Developers
Classifier: License :: OSI Approved :: GNU Affero General Public License v3 or later (AGPLv3+)
Classifier: Programming Language :: Python :: 3
Classifier: Topic :: Scientific/Engineering
Requires-Python: >=3.10
Requires-Dist: mne>=1.6.0
Requires-Dist: numpy<2.0,>=1.26.2
Requires-Dist: scipy>=1.11.4
Requires-Dist: matplotlib>=3.8.2
Requires-Dist: seaborn>=0.13.0
Requires-Dist: torch<2.5.0,>=2.1.0
Requires-Dist: lightning>=2.4.0
Requires-Dist: scikit-learn>=1.4.0
Requires-Dist: pyedflib>=0.1.36
Requires-Dist: omegaconf>=2.3.0
Requires-Dist: h5py>=3.10.0
Requires-Dist: pywavelets>=1.5.0
Requires-Dist: pyyaml>=6.0.2
Requires-Dist: py-simple-inject>=0.5.1
Requires-Dist: diskcache>=5.6.3
Requires-Dist: prettytable>=3.11.0
Requires-Dist: openpyxl>=3.1.5
Requires-Dist: rich>=13.9.2
Requires-Dist: torchmetrics>=1.4.3
